{
  "project_info": {
    "project_number": "22157376226",
    "project_id": "unieval-d9c4f",
    "storage_bucket": "unieval-d9c4f.appspot.com"
  },
  "client": [
    {
      "client_info": {
        "mobilesdk_app_id": "1:22157376226:android:d233141ac69d4167b27cbb",
        "android_client_info": {
          "package_name": "com.example.unieval"
        }
      },
      "oauth_client": [],
      "api_key": [
        {
          "current_key": "AIzaSyDKSXzAAJVguxJULo_l64MSlc8Oh6sRuC8"
        }
      ],
      "services": {
        "appinvite_service": {
          "other_platform_oauth_client": []
        }
      }
    }
  ],
  "configuration_version": "1"
}